pyamaha/__init__.py
pyamaha/__main__.py
pyamaha_yec-0.6.3.dist-info/licenses/LICENSE
pyamaha_yec-0.6.3.dist-info/METADATA
pyamaha_yec-0.6.3.dist-info/WHEEL
pyamaha_yec-0.6.3.dist-info/top_level.txt
pyamaha_yec-0.6.3.dist-info/RECORD
