Metadata-Version: 2.4
Name: pyamaha-yec
Version: 0.6.3
Summary: Python implementation of Yamaha Extended Control API Specification
Home-page: https://github.com/jackjpowell/pyamaha
Download-URL: https://github.com/jackjpowell/pyamaha/releases/tag/0.4
Author: Jack Powell
Author-email: jack.powell@gmail.com
Requires-Python: >=3.11
License-File: LICENSE
Requires-Dist: aiohttp>=3.12.13
Requires-Dist: requests>=2.32.4
Requires-Dist: setuptools>=80.9.0
Dynamic: author
Dynamic: author-email
Dynamic: download-url
Dynamic: home-page
Dynamic: license-file
